pmdt.py
pmdt-1.1.2.dist-info/licenses/LICENSE
pmdt-1.1.2.dist-info/METADATA
pmdt-1.1.2.dist-info/WHEEL
pmdt-1.1.2.dist-info/top_level.txt
pmdt-1.1.2.dist-info/RECORD
