Metadata-Version: 2.4
Name: pmdt
Version: 1.1.2
Summary: Project Management Digital Twin
Author-email: Filippo Maria Ottaviani <filippo.ottaviani@polito.it>
License: MIT
Project-URL: Homepage, https://github.com/filippomariaottaviani
Requires-Python: >=3.10
License-File: LICENSE
Requires-Dist: numpy>=1.24
Requires-Dist: pandas>=2.0
Dynamic: license-file
